__init__.py
pyphotomol/__init__.py
pyphotomol/main.py
pyphotomol/utils/__init__.py
pyphotomol/utils/data_import.py
pyphotomol/utils/helpers.py
pyphotomol/utils/palette.py
pyphotomol/utils/plotting.py
pyphotomol-0.1.5.dist-info/licenses/LICENSE
pyphotomol-0.1.5.dist-info/METADATA
pyphotomol-0.1.5.dist-info/WHEEL
pyphotomol-0.1.5.dist-info/top_level.txt
pyphotomol-0.1.5.dist-info/RECORD
