Metadata-Version: 2.4
Name: pyphotomol
Version: 0.1.5
Summary: Python package to analyse mass photometry data
Requires-Python: >=3.9
License-File: LICENSE
Requires-Dist: h5py>=3.14.0
Requires-Dist: kaleido>=1.0.0
Requires-Dist: matplotlib>=3.7.0
Requires-Dist: numpy>=2.0.2
Requires-Dist: pandas>=2.3.1
Requires-Dist: plotly>=6.2.0
Requires-Dist: scipy>=1.13.1
Provides-Extra: test
Requires-Dist: pytest>=7.0.0; extra == "test"
Requires-Dist: pytest-cov>=4.0.0; extra == "test"
Provides-Extra: docs
Requires-Dist: Sphinx>=7.0.0; extra == "docs"
Requires-Dist: pydata-sphinx-theme>=0.15.0; extra == "docs"
Requires-Dist: sphinx_design>=0.5.0; extra == "docs"
Requires-Dist: numpydoc>=1.6.0; extra == "docs"
Requires-Dist: sphinx_copybutton>=0.5.0; extra == "docs"
Requires-Dist: sphinx-tabs>=3.4.0; extra == "docs"
Provides-Extra: dev
Requires-Dist: pytest>=7.0.0; extra == "dev"
Requires-Dist: pytest-cov>=4.0.0; extra == "dev"
Requires-Dist: coverage-badge>=1.1.0; extra == "dev"
Requires-Dist: black>=23.0.0; extra == "dev"
Requires-Dist: flake8>=6.0.0; extra == "dev"
Requires-Dist: jupyter>=1.0.0; extra == "dev"
Requires-Dist: notebook>=6.0.0; extra == "dev"
Requires-Dist: ipykernel>=6.29.5; extra == "dev"
Requires-Dist: Sphinx>=7.0.0; extra == "dev"
Requires-Dist: pydata-sphinx-theme>=0.15.0; extra == "dev"
Requires-Dist: sphinx_design>=0.5.0; extra == "dev"
Requires-Dist: numpydoc>=1.6.0; extra == "dev"
Requires-Dist: sphinx_copybutton>=0.5.0; extra == "dev"
Requires-Dist: sphinx-tabs>=3.4.0; extra == "dev"
Dynamic: license-file
